bitmat/__init__.py
bitmat/bitlinear.py
bitmat/triton_kernels/__init__.py
bitmat/triton_kernels/bitmat_kernel.py
bitmat/triton_kernels/rmsnorm_kernel.py
bitmat/triton_kernels/utils.py
bitmat/utils/__init__.py
bitmat/utils/bitmat.py
bitmat/utils/convert_hf_model.py
bitmat/utils/custom_autotune.py
bitmat/utils/pack_model_before_save.py
bitmat/utils/packing.py
bitmat/utils/rmsnorm.py
bitmat/utils/modeling/__init__.py
bitmat/utils/modeling/automodel.py
bitmat/utils/modeling/model_hijacks/__init__.py
bitmat/utils/modeling/model_hijacks/gemma_1_58b.py
bitmat/utils/modeling/model_hijacks/llama_1_58b.py
bitmat/utils/modeling/model_hijacks/mistral_1_58b.py
bitmat_tl-0.3.7.dist-info/LICENSE
bitmat_tl-0.3.7.dist-info/METADATA
bitmat_tl-0.3.7.dist-info/WHEEL
bitmat_tl-0.3.7.dist-info/top_level.txt
bitmat_tl-0.3.7.dist-info/RECORD
